huaweicloudsdkcodeartsrepo/__init__.py
huaweicloudsdkcodeartsrepo/v3/__init__.py
huaweicloudsdkcodeartsrepo/v3/codeartsrepo_async_client.py
huaweicloudsdkcodeartsrepo/v3/codeartsrepo_client.py
huaweicloudsdkcodeartsrepo/v3/model/__init__.py
huaweicloudsdkcodeartsrepo/v3/model/add_deploy_key_request.py
huaweicloudsdkcodeartsrepo/v3/model/add_deploy_key_request_body.py
huaweicloudsdkcodeartsrepo/v3/model/add_deploy_key_response.py
huaweicloudsdkcodeartsrepo/v3/model/add_deploy_key_v2_request.py
huaweicloudsdkcodeartsrepo/v3/model/add_deploy_key_v2_response.py
huaweicloudsdkcodeartsrepo/v3/model/add_hooks_request.py
huaweicloudsdkcodeartsrepo/v3/model/add_hooks_response.py
huaweicloudsdkcodeartsrepo/v3/model/add_protect_access_level.py
huaweicloudsdkcodeartsrepo/v3/model/add_protect_branch_v2_request.py
huaweicloudsdkcodeartsrepo/v3/model/add_protect_branch_v2_response.py
huaweicloudsdkcodeartsrepo/v3/model/add_protect_request.py
huaweicloudsdkcodeartsrepo/v3/model/add_protect_response.py
huaweicloudsdkcodeartsrepo/v3/model/add_repo_members_request.py
huaweicloudsdkcodeartsrepo/v3/model/add_repo_members_response.py
huaweicloudsdkcodeartsrepo/v3/model/add_ssh_key_request.py
huaweicloudsdkcodeartsrepo/v3/model/add_ssh_key_request_body.py
huaweicloudsdkcodeartsrepo/v3/model/add_ssh_key_response.py
huaweicloudsdkcodeartsrepo/v3/model/add_tag_v2_request.py
huaweicloudsdkcodeartsrepo/v3/model/add_tag_v2_response.py
huaweicloudsdkcodeartsrepo/v3/model/add_tags_request.py
huaweicloudsdkcodeartsrepo/v3/model/add_tags_response.py
huaweicloudsdkcodeartsrepo/v3/model/approval_action_type_dto.py
huaweicloudsdkcodeartsrepo/v3/model/approval_merge_request_approvers_item.py
huaweicloudsdkcodeartsrepo/v3/model/approval_user_dto.py
huaweicloudsdkcodeartsrepo/v3/model/approver_basic_dto.py
huaweicloudsdkcodeartsrepo/v3/model/associate_issues_request.py
huaweicloudsdkcodeartsrepo/v3/model/associate_issues_request_body.py
huaweicloudsdkcodeartsrepo/v3/model/associate_issues_response.py
huaweicloudsdkcodeartsrepo-3.1.184.dist-info/METADATA
huaweicloudsdkcodeartsrepo-3.1.184.dist-info/WHEEL
huaweicloudsdkcodeartsrepo-3.1.184.dist-info/licenses/LICENSE
huaweicloudsdkcodeartsrepo-3.1.184.dist-info/RECORD
